parsec_integration/__init__.py
parsec_integration/core.py
parsec_integration/errors.py
parsec_integration/main.py
parsec_integration/test.py
parsec_integration/dto/__init__.py
parsec_integration/dto/dto.py
parsec_integration/dto/validators.py
parsec_integration-0.1.8.dist-info/METADATA
parsec_integration-0.1.8.dist-info/WHEEL
parsec_integration-0.1.8.dist-info/top_level.txt
parsec_integration-0.1.8.dist-info/RECORD
